kuat/__init__.py
kuat/angle_axis.py
kuat/euclidean.py
kuat/matrix44.py
kuat/quaternion.py
kuat/rotation33.py
kuat/transform.py
kuat/util.py
kuat-0.17.0.dist-info/LICENSE
kuat-0.17.0.dist-info/METADATA
kuat-0.17.0.dist-info/WHEEL
kuat-0.17.0.dist-info/top_level.txt
kuat-0.17.0.dist-info/zip-safe
kuat-0.17.0.dist-info/RECORD
