Metadata-Version: 2.2
Name: kuat
Version: 0.17.0
Summary: Quaternions in PyTorch (part of NVIDIA Kaolin)
Home-page: https://github.com/emaballarin/kuat
Author: ['Emanuele Ballarin', 'NVIDIA']
Author-email: emanuele@ballarin.cc
License: Apache License, Version 2.0
Keywords: Deep Learning,Machine Learning,Computer Vision,Differentiable Programming,Mathematics,Computer Graphics,Robotics
Classifier: Development Status :: 4 - Beta
Classifier: Topic :: Scientific/Engineering :: Artificial Intelligence
Classifier: Environment :: Console
Classifier: Programming Language :: Python :: 3
Classifier: License :: OSI Approved :: Apache Software License
Requires-Python: >=3.10
License-File: LICENSE
Requires-Dist: torch>=2
Dynamic: author
Dynamic: author-email
Dynamic: classifier
Dynamic: description
Dynamic: description-content-type
Dynamic: home-page
Dynamic: keywords
Dynamic: license
Dynamic: requires-dist
Dynamic: requires-python
Dynamic: summary
